relative_include/__init__.py
relative_include/__main__.py
relative_include/_version.py
relative_include/relative_include.py
relative_include-1.0.1.dist-info/LICENSE
relative_include-1.0.1.dist-info/METADATA
relative_include-1.0.1.dist-info/WHEEL
relative_include-1.0.1.dist-info/entry_points.txt
relative_include-1.0.1.dist-info/top_level.txt
relative_include-1.0.1.dist-info/RECORD
