Metadata-Version: 2.1
Name: relative-include
Version: 1.0.1
Summary: Makes include paths for a C/C++ lib relative
Home-page: https://github.com/vChavezB/include-relative
Author: Victor Chavez
Author-email: vchavezb@protonmail.com
License: MIT
Platform: UNKNOWN
Classifier: License :: OSI Approved :: GNU General Public License v3 (GPLv3)
Classifier: Programming Language :: Python
Classifier: Programming Language :: Python :: 3
Classifier: Operating System :: OS Independent
License-File: LICENSE
